{
  "version": 1,
  "skills": {
    "impeccable": {
      "source": "pbakaus/impeccable",
      "sourceType": "github",
      "skillPath": ".agents/skills/impeccable/SKILL.md",
      "computedHash": "b45b2876561b6fe330ef2cdcb793750473584dff3d27de0744cfefab3e62a0fb"
    },
    "redesign-existing-projects": {
      "source": "leonxlnx/taste-skill",
      "sourceType": "github",
      "skillPath": "skills/redesign-skill/SKILL.md",
      "computedHash": "47eced3e960a2c961d3cbee11fa1216264f589344b586a5cbd03967cd6b9c54b"
    }
  }
}
